omni_lpr/__init__.py
omni_lpr/__main__.py
omni_lpr/api_models.py
omni_lpr/errors.py
omni_lpr/event_store.py
omni_lpr/mcp.py
omni_lpr/py.typed
omni_lpr/rest.py
omni_lpr/settings.py
omni_lpr/tools.py
omni_lpr-0.3.4.dist-info/METADATA
omni_lpr-0.3.4.dist-info/WHEEL
omni_lpr-0.3.4.dist-info/entry_points.txt
omni_lpr-0.3.4.dist-info/licenses/LICENSE
omni_lpr-0.3.4.dist-info/RECORD
