Metadata-Version: 2.4
Name: omni-lpr
Version: 0.3.4
Summary: A multi-interface (REST and MCP) server for automatic license plate recognition
License: MIT
License-File: LICENSE
Keywords: alpr,license plate recognition,automatic license plate recognition,computer vision,rest-api,mcp,microservice,onnx,cuda
Author: Hassan Abedi
Author-email: hassan.abedi.t+omnilpr@gmail.com
Maintainer: Hassan Abedi
Maintainer-email: hassan.abedi.t+omnilpr@gmail.com
Requires-Python: >=3.10,<4.0
Classifier: Development Status :: 4 - Beta
Classifier: Intended Audience :: Developers
Classifier: License :: OSI Approved :: MIT License
Classifier: Operating System :: OS Independent
Classifier: Topic :: Internet :: WWW/HTTP :: WSGI :: Application
Classifier: Topic :: Scientific/Engineering :: Image Recognition
Classifier: Topic :: Software Development :: Libraries :: Python Modules
Classifier: Topic :: Utilities
Classifier: Programming Language :: Python :: 3
Classifier: Programming Language :: Python :: 3.10
Classifier: Programming Language :: Python :: 3.11
Classifier: Programming Language :: Python :: 3.12
Classifier: Programming Language :: Python :: 3.13
Provides-Extra: cuda
Provides-Extra: dev
Provides-Extra: openvino
Requires-Dist: asgi-lifespan[dev] (>=2.1.0,<3.0.0) ; extra == "dev"
Requires-Dist: async-lru (>=2.0.4,<3.0.0)
Requires-Dist: click (>=8.2.1,<9.0.0)
Requires-Dist: fast-alpr[onnx-gpu] (>=0.3.0,<0.4.0) ; extra == "cuda"
Requires-Dist: fast-alpr[onnx-openvino] (>=0.3.0,<0.4.0) ; extra == "openvino"
Requires-Dist: fast-alpr[onnx] (>=0.3.0,<0.4.0)
Requires-Dist: gunicorn (>=23.0.0,<24.0.0)
Requires-Dist: httpx (>=0.28.1,<0.29.0)
Requires-Dist: mcp[cli] (>=1.12.3,<2.0.0)
Requires-Dist: mypy (>=1.11.1,<2.0.0) ; extra == "dev"
Requires-Dist: opencv-python (>=4.12.0.88,<5.0.0.0)
Requires-Dist: pillow (>=11.3.0,<12.0.0)
Requires-Dist: pre-commit (>=4.2.0,<5.0.0) ; extra == "dev"
Requires-Dist: pydantic (>=2.11.7,<3.0.0)
Requires-Dist: pydantic-settings (>=2.10.1,<3.0.0)
Requires-Dist: pytest (>=8.0.1,<9.0.0) ; extra == "dev"
Requires-Dist: pytest-asyncio (>=1.1.0,<2.0.0) ; extra == "dev"
Requires-Dist: pytest-cov (>=6.0.0,<7.0.0) ; extra == "dev"
Requires-Dist: pytest-mock (>=3.14.0,<4.0.0) ; extra == "dev"
Requires-Dist: python-dotenv (>=1.1.0,<2.0.0)
Requires-Dist: python-json-logger (>=3.3.0,<4.0.0)
Requires-Dist: ruff (>=0.9.3,<1.0.0) ; extra == "dev"
Requires-Dist: spectree[starlette] (>=1.5.4,<2.0.0)
Project-URL: Documentation, https://github.com/habedi/omni-lpr/blob/main/README.md
Project-URL: Repository, https://github.com/habedi/omni-lpr
